maquina/probador_maquina.v
module probador_maquina(

    output reg clk,
    output reg reset,
    output reg init,

    //umbrales

    output reg   [7:0]           bajo,                   //umbral bajo
    output reg   [7:0]           alto,                   //umbral alto

    output reg [3:0]        estado_actual,         //
    output reg [3:0]        sig_estado,

    output reg [7:0]             empty_fifos,

    input              active_out,
    input              next_active,
    input              idle_out,
    input              next_idle,

    input   [7:0]           bajo_out,                  
    input   [7:0]           alto_out,

    input   [7:0]           next_bajo,                  
    input   [7:0]           next_alto         
);


    initial begin

    $dumpfile("probmaq.vcd");
    $dumpvars();
    reset <= 0;
    init<=0;
    bajo<=0000;
    alto<=0000;
    empty_fifos[0] <= 0;
    empty_fifos[1] <= 0;
    empty_fifos[2] <= 0;
    empty_fifos[3] <= 0;
    empty_fifos[4] <= 0;
    empty_fifos[5] <= 0;
    empty_fifos[6] <= 0;
    empty_fifos[7] <= 0;
    empty_fifos[8] <= 0;
    
    @(posedge clk);
    reset <= 0;
    
    @(posedge clk);
    reset <= 1;
    
    @(posedge clk);
    bajo<=00111000;
    alto<=01110000;

    @(posedge clk);
    init<=1;
    bajo<=00111110;
    alto<=01110010;
    
    @(posedge clk);
    init<=1;

    @(posedge clk);
    @(posedge clk);
    
    @(posedge clk);
    empty_fifos[0] <= 0;
    empty_fifos[1] <= 0;
    empty_fifos[2] <= 0;
    empty_fifos[3] <= 0;
    empty_fifos[4] <= 0;
    empty_fifos[5] <= 0;
    empty_fifos[6] <= 0;
    empty_fifos[7] <= 0;
    empty_fifos[8] <= 0;

    @(posedge clk);
    @(posedge clk);
    bajo<=00111000;
    alto<=01110000;


    @(posedge clk);
    @(posedge clk);
    bajo<=00111000;
    alto<=01110000;

    @(posedge clk);
    @(posedge clk);
    reset <= 0;
    @(posedge clk);
    @(posedge clk);
    $finish;
  end

  initial clk <= 0;
  always #1 clk <= ~clk;
endmodule

maquina/maquina_de_estados.v
module maquina_de_estados(
    input clk,
    input reset,
    input init,

    //umbrales

    input   [7:0]           bajo,                   //umbral bajo
    input   [7:0]           alto,                   //umbral alto

    output reg [3:0]        estado_actual,         //
    output reg [3:0]        sig_estado,

    input [7:0]             empty_fifos,

    output reg              active_out,
    output reg              next_active,
    output reg              idle_out,
    output reg              next_idle,

    output reg  [7:0]           bajo_out,                  
    output reg  [7:0]           alto_out,

    output reg   [7:0]           next_bajo,                  
    output reg   [7:0]           next_alto                  


      
);


/************************** ESTADOS ONE HOT ******************************/

    parameter RESET =       4'b0000; //1
    parameter INIT =        4'b0001; //2
    parameter IDLE =        4'b0010; //3
    parameter ACTIVE =      4'b0011; //4

/***********************************************************************/

   

/***********************************************************************/
    reg [7:0] FIFO_empties;


    always @(posedge clk) begin
        if (reset == 1) 
        begin
            
            estado_actual   <= RESET;
            active_out      <= 0;
            idle_out        <= 0;
            bajo_out        <=0;
            alto_out        <=0;
            
        end

        else begin
            
            estado_actual <= sig_estado;
            
            
            
            
        end
    end


    always @(*) begin
        // Unir errores y empities de FIFOS:
        FIFO_empties[0] = empty_fifos[0]; 
        FIFO_empties[1] = empty_fifos[1]; 
        FIFO_empties[2] = empty_fifos[2]; 
        FIFO_empties[3] = empty_fifos[3]; 
        FIFO_empties[4] = empty_fifos[4]; 
        FIFO_empties[5] = empty_fifos[5]; 
        FIFO_empties[6] = empty_fifos[6]; 
        FIFO_empties[7] = empty_fifos[7];

      
        
       
       case(estado_actual)

            RESET:begin idle_out=0;
                    

                    if (reset == 0) sig_estado = INIT;  
                     
                    else sig_estado = RESET;
                    
                end 
//SEÑAL INIT VIENE DEL PROBADOR
            INIT: begin idle_out=0;
                    bajo_out=bajo_out;
                    alto_out=alto_out;

                    if (!init) begin
                        sig_estado = IDLE;
                        
                    end
                    else if (reset) sig_estado = RESET;  
                    else if (!reset && init)begin
                        next_alto = alto;
                        next_bajo = bajo;
                        sig_estado = INIT; 
                    end 

                end 
            
            IDLE: begin
                    idle_out=1;
                    alto_out=alto;
                    bajo_out=bajo;
                    if (reset == 1) begin
                        sig_estado = RESET;
                    end
                    else if (!reset && init)begin
                        sig_estado=INIT;
                    end
                    else if (FIFO_empties== 8'b11111111)
                    begin
                        sig_estado = IDLE;
                    end                  
                    
                    else begin
                        sig_estado = ACTIVE;
                    end

                    
                    
                end

            ACTIVE: begin 
                    idle_out=0;
                    bajo_out=bajo_out;
                    alto_out=alto_out;
                    if (reset == 1) begin
                        sig_estado = RESET;
                    end
                    else if (!reset && init)begin
                        sig_estado=INIT;
                    end
                    
                    else if(FIFO_empties==  8'b11111111 )begin   
                        sig_estado = IDLE;
                    end
                    else begin
                        sig_estado = ACTIVE;
                    end


                    
                end
            

            default: 
            
            begin
                sig_estado = RESET;
            end 
        
        endcase    
    end
    
endmodule

maquina/banco.v
`include "probador_maquina.v"
`include "maquina_de_estados.v"

module banco();

    wire clk;
    wire reset;
    wire init;

    //umbrales

    wire   [7:0]           bajo;                   //umbral bajo
    wire   [7:0]           alto;                   //umbral alto

    wire [3:0]        estado_actual;         //
    wire [3:0]        sig_estado;

    wire [7:0]             empty_fifos;

    wire              active_out;
    wire              next_active;
    wire              idle_out;
    wire              next_idle;

    wire   [7:0]           bajo_out;                  
    wire   [7:0]           alto_out;

    wire   [7:0]           next_bajo;                  
    wire   [7:0]           next_alto;

maquina_de_estados maq(/*AUTOINST*/

    .clk                (clk),
    .reset              (reset),
    .init               (init),

    //umbrales

    .bajo               (bajo),                   //umbral bajo
    .alto               (alto),                   //umbral alto

    .estado_actual      (estado_actual),         //
    .sig_estado         (sig_estado),

    .empty_fifos        (empty_fifos [7:0]),

    .active_out         (active_out),
    .next_active        (next_active),
    .idle_out           (idle_out),
    .next_idle          (next_idle),

    .bajo_out           (bajo_out),                  
    .alto_out           (alto_out),

    .next_bajo          (next_bajo),                  
    .next_alto          (next_alto)    
);

probador_maquina maqprob(/*AUTOINST*/

    .clk                (clk),
    .reset              (reset),
    .init               (init),

    //umbrales

    .bajo               (bajo),                   //umbral bajo
    .alto               (alto),                   //umbral alto

    .estado_actual      (estado_actual),         //
    .sig_estado         (sig_estado),

    .empty_fifos        (empty_fifos [7:0]),

    .active_out         (active_out),
    .next_active        (next_active),
    .idle_out           (idle_out),
    .next_idle          (next_idle),

    .bajo_out           (bajo_out),                  
    .alto_out           (alto_out),

    .next_bajo          (next_bajo),                  
    .next_alto          (next_alto)    

);

endmodule

maquina/probmaq.vcd
$date
	Mon Jul 12 10:22:45 2021
$end
$version
	Icarus Verilog
$end
$timescale
	1s
$end
$scope module banco $end
$var wire 4 ! estado_actual [3:0] $end
$var wire 4 " sig_estado [3:0] $end
$var wire 1 # reset $end
$var wire 1 $ next_idle $end
$var wire 8 % next_bajo [7:0] $end
$var wire 8 & next_alto [7:0] $end
$var wire 1 ' next_active $end
$var wire 1 ( init $end
$var wire 1 ) idle_out $end
$var wire 8 * empty_fifos [7:0] $end
$var wire 1 + clk $end
$var wire 8 , bajo_out [7:0] $end
$var wire 8 - bajo [7:0] $end
$var wire 8 . alto_out [7:0] $end
$var wire 8 / alto [7:0] $end
$var wire 1 0 active_out $end
$scope module maq $end
$var wire 1 # reset $end
$var wire 1 ( init $end
$var wire 8 1 empty_fifos [7:0] $end
$var wire 1 + clk $end
$var wire 8 2 bajo [7:0] $end
$var wire 8 3 alto [7:0] $end
$var reg 8 4 FIFO_empties [7:0] $end
$var reg 1 0 active_out $end
$var reg 8 5 alto_out [7:0] $end
$var reg 8 6 bajo_out [7:0] $end
$var reg 4 7 estado_actual [3:0] $end
$var reg 1 ) idle_out $end
$var reg 1 ' next_active $end
$var reg 8 8 next_alto [7:0] $end
$var reg 8 9 next_bajo [7:0] $end
$var reg 1 $ next_idle $end
$var reg 4 : sig_estado [3:0] $end
$upscope $end
$scope module maqprob $end
$var wire 1 0 active_out $end
$var wire 8 ; alto_out [7:0] $end
$var wire 8 < bajo_out [7:0] $end
$var wire 1 ) idle_out $end
$var wire 1 ' next_active $end
$var wire 8 = next_alto [7:0] $end
$var wire 8 > next_bajo [7:0] $end
$var wire 1 $ next_idle $end
$var reg 8 ? alto [7:0] $end
$var reg 8 @ bajo [7:0] $end
$var reg 1 + clk $end
$var reg 8 A empty_fifos [7:0] $end
$var reg 4 B estado_actual [3:0] $end
$var reg 1 ( init $end
$var reg 1 # reset $end
$var reg 4 C sig_estado [3:0] $end
$upscope $end
$upscope $end
$enddefinitions $end
#0
$dumpvars
bx C
bx B
b0 A
b0 @
b0 ?
bx >
bx =
bx <
bx ;
b0 :
bx 9
bx 8
bx 7
bx 6
bx 5
b0 4
b0 3
b0 2
b0 1
x0
b0 /
bx .
b0 -
bx ,
0+
b0 *
x)
0(
x'
bx &
bx %
x$
0#
bx "
bx !
$end
#1
b1 :
b0 7
1+
#2
0+
#3
b0 %
b0 9
b0 >
b0 &
b0 8
b0 =
1#
b1 7
1+
#4
0+
#5
0$
0'
b0 :
b0 .
b0 5
b0 ;
b0 ,
b0 6
b0 <
0)
00
b0 7
b11110000 /
b11110000 3
b11110000 ?
b10011000 -
b10011000 2
b10011000 @
1+
#6
0+
#7
b11111010 /
b11111010 3
b11111010 ?
b110 -
b110 2
b110 @
1(
1+
#8
0+
#9
1+
#10
0+
#11
1+
#12
0+
#13
1+
#14
0+
#15
1+
#16
0+
#17
1+
#18
0+
#19
b11110000 /
b11110000 3
b11110000 ?
b10011000 -
b10011000 2
b10011000 @
1+
#20
0+
#21
1+
#22
0+
#23
1+
#24
0+
#25
1+
#26
0+
#27
b1 :
0#
1+
#28
0+
#29
b10 :
b1 7
1+
#30
0+
#31
1$
b10 7
1+
