MaquinaEstados/probador_maquina.v
module probador_maquina(

    output reg clk,
    output reg reset,
    output reg init,

    //umbrales

    output reg   [2:0]           bajo,                   //umbral bajo
    output reg   [2:0]           alto,                   //umbral alto

    input  [3:0]        estado_actual,         //
    input [3:0]        sig_estado,

    output reg [7:0]             empty_fifos,

    input              active_out,
    input              next_active,
    input              idle_out,
    input              next_idle,

    input   [2:0]           bajo_out,                  
    input   [2:0]           alto_out,

    input   [2:0]           next_bajo,                  
    input   [2:0]           next_alto         
);


    initial begin

    $dumpfile("probmaq.vcd");
    $dumpvars();
    reset <= 1;
    init<=0;
    bajo<=000;
    alto<=110;
    empty_fifos=8'hFF;
    
    @(posedge clk);
    reset <= 0;
    init<=1;
    
    @(posedge clk);
    reset <= 0;
    init<=0;
    
    @(posedge clk);
    bajo<=000;
    alto<=110;

    @(posedge clk);
    
    bajo<=001;
    alto<=111;
    
    @(posedge clk);
   

    @(posedge clk);
    @(posedge clk);
    
    @(posedge clk);
    empty_fifos[0] <= 0;
    empty_fifos[1] <= 0;
    empty_fifos[2] <= 0;
    empty_fifos[3] <= 0;
    empty_fifos[4] <= 0;
    empty_fifos[5] <= 0;
    empty_fifos[6] <= 0;
    empty_fifos[7] <= 0;
    empty_fifos[8] <= 0;

    @(posedge clk);
    @(posedge clk);
    bajo<=001;
    alto<=111;
    init<=1;

    @(posedge clk);
    @(posedge clk);
    bajo<=000;
    alto<=110;

    @(posedge clk);
    @(posedge clk);
    reset <= 0;
    @(posedge clk);
    @(posedge clk);
    $finish;
  end

  initial clk <= 0;
  always #1 clk <= ~clk;
endmodule

maquina/maquina_de_estados.v
module maquina_de_estados(
    input clk,
    input reset,
    input init,

    //umbrales

    input   [2:0]           bajo,                   //umbral bajo
    input   [2:0]           alto,                   //umbral alto

    output reg [3:0]        estado_actual,         //
    output reg [3:0]        sig_estado,

    input [7:0]             empty_fifos,

    output reg              active_out,
    output reg              next_active,
    output reg              idle_out,
    output reg              next_idle,

    output reg  [2:0]           bajo_out,                  
    output reg  [2:0]           alto_out,

    output reg   [7:0]           next_bajo,                  
    output reg   [7:0]           next_alto                  


      
);


/************************** ESTADOS ONE HOT ******************************/

    parameter RESET =       4'b0000; //1
    parameter INIT =        4'b0001; //2
    parameter IDLE =        4'b0010; //3
    parameter ACTIVE =      4'b0011; //4

/***********************************************************************/

   

/***********************************************************************/
    reg [7:0] FIFO_empties;


    always @(posedge clk) begin
        if (reset == 1) 
        begin
            
            estado_actual   <= RESET;
            active_out      <= 0;
            idle_out        <= 0;
            bajo_out        <=0;
            alto_out        <=0;
            
        end

        else begin
            
            estado_actual <= sig_estado;
            
            
            
            
        end
    end


    always @(*) begin
        // Unir errores y empities de FIFOS:
        FIFO_empties[0] = empty_fifos[0]; 
        FIFO_empties[1] = empty_fifos[1]; 
        FIFO_empties[2] = empty_fifos[2]; 
        FIFO_empties[3] = empty_fifos[3]; 
        FIFO_empties[4] = empty_fifos[4]; 
        FIFO_empties[5] = empty_fifos[5]; 
        FIFO_empties[6] = empty_fifos[6]; 
        FIFO_empties[7] = empty_fifos[7];

      
        
       
       case(estado_actual)

            RESET:begin idle_out=0;
                    

                    if (reset == 0) sig_estado = INIT;  
                     
                    else sig_estado = RESET;
                    
                end 
//SEÑAL INIT VIENE DEL PROBADOR
            INIT: begin idle_out=0;
                    bajo_out=bajo_out;
                    alto_out=alto_out;

                    if (!init) begin
                        sig_estado = IDLE;
                        
                    end
                    else if (reset) sig_estado = RESET;  
                    else if (!reset && init)begin
                        next_alto = alto;
                        next_bajo = bajo;
                        sig_estado = INIT; 
                    end 

                end 
            
            IDLE: begin
                    idle_out=1;
                    alto_out=alto;
                    bajo_out=bajo;
                    if (reset == 1) begin
                        sig_estado = RESET;
                    end
                    else if (!reset && init)begin
                        sig_estado=INIT;
                    end
                    else if (FIFO_empties== 8'b11111111)
                    begin
                        sig_estado = IDLE;
                    end                  
                    
                    else begin
                        sig_estado = ACTIVE;
                    end

                    
                    
                end

            ACTIVE: begin 
                    idle_out=0;
                    bajo_out=bajo_out;
                    alto_out=alto_out;
                    if (reset == 1) begin
                        sig_estado = RESET;
                    end
                    else if (!reset && init)begin
                        sig_estado=INIT;
                    end
                    
                    else if(FIFO_empties==  8'b11111111 )begin   
                        sig_estado = IDLE;
                    end
                    else begin
                        sig_estado = ACTIVE;
                    end


                    
                end
            

            default: 
            
            begin
                sig_estado = RESET;
            end 
        
        endcase    
    end
    
endmodule

maquina/banco.v
`include "probador_maquina.v"
`include "maquina_de_estados.v"

module banco();

    wire clk;
    wire reset;
    wire init;

    //umbrales

    wire   [2:0]           bajo;                   //umbral bajo
    wire   [2:0]           alto;                   //umbral alto

    wire [3:0]        estado_actual;         //
    wire [3:0]        sig_estado;

    wire [7:0]             empty_fifos;

    wire              active_out;
    wire              next_active;
    wire              idle_out;
    wire              next_idle;

    wire   [7:0]           bajo_out;                  
    wire   [7:0]           alto_out;

    wire   [7:0]           next_bajo;                  
    wire   [7:0]           next_alto;

maquina_de_estados maq(/*AUTOINST*/

    .clk                (clk),
    .reset              (reset),
    .init               (init),

    //umbrales

    .bajo               (bajo),                   //umbral bajo
    .alto               (alto),                   //umbral alto

    .estado_actual      (estado_actual),         //
    .sig_estado         (sig_estado),

    .empty_fifos        (empty_fifos [7:0]),

    .active_out         (active_out),
    .next_active        (next_active),
    .idle_out           (idle_out),
    .next_idle          (next_idle),

    .bajo_out           (bajo_out),                  
    .alto_out           (alto_out),

    .next_bajo          (next_bajo),                  
    .next_alto          (next_alto)    
);

probador_maquina maqprob(/*AUTOINST*/

    .clk                (clk),
    .reset              (reset),
    .init               (init),

    //umbrales

    .bajo               (bajo),                   //umbral bajo
    .alto               (alto),                   //umbral alto

    .estado_actual      (estado_actual),         //
    .sig_estado         (sig_estado),

    .empty_fifos        (empty_fifos [7:0]),

    .active_out         (active_out),
    .next_active        (next_active),
    .idle_out           (idle_out),
    .next_idle          (next_idle),

    .bajo_out           (bajo_out),                  
    .alto_out           (alto_out),

    .next_bajo          (next_bajo),                  
    .next_alto          (next_alto)    

);

endmodule

maquina/probmaq.vcd
$date
	Mon Jul 12 23:19:51 2021
$end
$version
	Icarus Verilog
$end
$timescale
	1s
$end
$scope module banco $end
$var wire 4 ! sig_estado [3:0] $end
$var wire 1 " reset $end
$var wire 1 # next_idle $end
$var wire 8 $ next_bajo [7:0] $end
$var wire 8 % next_alto [7:0] $end
$var wire 1 & next_active $end
$var wire 1 ' init $end
$var wire 1 ( idle_out $end
$var wire 4 ) estado_actual [3:0] $end
$var wire 8 * empty_fifos [7:0] $end
$var wire 1 + clk $end
$var wire 8 , bajo_out [7:0] $end
$var wire 3 - bajo [2:0] $end
$var wire 8 . alto_out [7:0] $end
$var wire 3 / alto [2:0] $end
$var wire 1 0 active_out $end
$scope module maq $end
$var wire 1 " reset $end
$var wire 1 ' init $end
$var wire 8 1 empty_fifos [7:0] $end
$var wire 1 + clk $end
$var wire 3 2 bajo [2:0] $end
$var wire 3 3 alto [2:0] $end
$var reg 8 4 FIFO_empties [7:0] $end
$var reg 1 0 active_out $end
$var reg 3 5 alto_out [2:0] $end
$var reg 3 6 bajo_out [2:0] $end
$var reg 4 7 estado_actual [3:0] $end
$var reg 1 ( idle_out $end
$var reg 1 & next_active $end
$var reg 8 8 next_alto [7:0] $end
$var reg 8 9 next_bajo [7:0] $end
$var reg 1 # next_idle $end
$var reg 4 : sig_estado [3:0] $end
$upscope $end
$scope module maqprob $end
$var wire 1 0 active_out $end
$var wire 3 ; alto_out [2:0] $end
$var wire 3 < bajo_out [2:0] $end
$var wire 4 = estado_actual [3:0] $end
$var wire 1 ( idle_out $end
$var wire 1 & next_active $end
$var wire 3 > next_alto [2:0] $end
$var wire 3 ? next_bajo [2:0] $end
$var wire 1 # next_idle $end
$var wire 4 @ sig_estado [3:0] $end
$var reg 3 A alto [2:0] $end
$var reg 3 B bajo [2:0] $end
$var reg 1 + clk $end
$var reg 8 C empty_fifos [7:0] $end
$var reg 1 ' init $end
$var reg 1 " reset $end
$upscope $end
$upscope $end
$enddefinitions $end
#0
$dumpvars
b11111111 C
b0 B
b110 A
b0 @
bx ?
bx >
bx =
bx <
bx ;
b0 :
bx 9
bx 8
bx 7
bx 6
bx 5
b11111111 4
b110 3
b0 2
b11111111 1
x0
b110 /
b0xxx .
b0 -
b0xxx ,
0+
b11111111 *
bx )
x(
0'
x&
bx %
bx $
x#
1"
b0 !
$end
#1
b0 ;
b0 <
b1 !
b1 :
b1 @
b0 .
b0 5
b0 ,
b0 6
0(
00
b0 )
b0 7
b0 =
1'
0"
1+
#2
0+
#3
b10 !
b10 :
b10 @
0'
b1 )
b1 7
b1 =
1+
#4
0+
#5
b110 ;
b110 .
b110 5
1(
b10 )
b10 7
b10 =
1+
#6
0+
#7
b1 <
b111 ;
b1 ,
b1 6
b111 .
b111 5
b111 /
b111 3
b111 A
b1 -
b1 2
b1 B
1+
#8
0+
#9
1+
#10
0+
#11
1+
#12
0+
#13
1+
#14
0+
#15
b11 !
b11 :
b11 @
b0 4
b0 *
b0 1
b0 C
1+
#16
0+
#17
0(
b11 )
b11 7
b11 =
1+
#18
0+
#19
b1 !
b1 :
b1 @
1'
1+
#20
0+
#21
b1 ?
b111 >
b1 $
b1 9
b111 %
b111 8
b1 )
b1 7
b1 =
1+
#22
0+
#23
b0 ?
b110 >
b0 $
b0 9
b110 %
b110 8
b110 /
b110 3
b110 A
b0 -
b0 2
b0 B
1+
