RoundRobin/probador_roundRobin.v

module probador_roundRobin(

	output reg  clk, reset, 

    // Entradas de alimentación de los fifos

    output reg  almost_full_P0,
    output reg  almost_full_P1,
    output reg  almost_full_P2,
    output reg  almost_full_P3,

    output reg  empty_P0,
    output reg  empty_P1,
    output reg  empty_P2,
    output reg  empty_P3,
    output reg  empty_P4,
    output reg  empty_P5,
    output reg  empty_P6,
    output reg  empty_P7,

    // Salidas para el control de los Fifos
            
    input pop_F0,
    input pop_F1,
    input pop_F2,
    input pop_F3,

    input push_F0,
    input push_F1,
    input push_F2,
    input push_F3,

    // Datos de salida y entrada de los fifos


    input pop_F0_sint,
    input pop_F1_sint,
    input pop_F2_sint,
    input pop_F3_sint,

    input push_F0_sint,
    input push_F1_sint,
    input push_F2_sint,
    input push_F3_sint
    );


	initial begin
	$dumpfile("roundRobin.vcd");
	$dumpvars;

	clk <= 0;   
	reset <= 1;

    almost_full_P0<=0;
    almost_full_P1<=0;
    almost_full_P2<=0;
    almost_full_P3<=0;


    empty_P0 <= 0;
    empty_P1 <= 0;
    empty_P2 <= 0;
    empty_P3 <= 0;

    @(posedge clk);
	reset <= 0;

    

    empty_P0 <= 0;
    empty_P1 <= 0;
    empty_P2 <= 0;
    empty_P3 <= 0;
    @(posedge clk);
    empty_P0 <= 1;
    empty_P1 <= 0;
    empty_P2 <= 0;
    empty_P3 <= 0;    
	@(posedge clk);
    empty_P0 <= 1;
    empty_P1 <= 1;
    empty_P2 <= 0;
    empty_P3 <= 0; 

	@(posedge clk);
    empty_P0 <= 1;
    empty_P1 <= 1;
    empty_P2 <= 1;
    empty_P3 <= 0;     
	@(posedge clk);
    empty_P0 <= 1;
    empty_P1 <= 1;
    empty_P2 <= 1;
    empty_P3 <= 1;     
    @(posedge clk);

    empty_P0 <= 0;
    empty_P1 <= 0;
    empty_P2 <= 0;
    empty_P3 <= 0;
    @(posedge clk);

	@(posedge clk);
	reset  <= 0;


    empty_P0 <= 0;
    empty_P1 <= 0;
    empty_P2 <= 0;
    empty_P3 <= 0;
    empty_P4 <= 0;
    empty_P5 <= 0;
    empty_P6 <= 0;
    empty_P7 <= 0;

	@(posedge clk);
	reset  <= 0;
	@(posedge clk);
    almost_full_P0<=1;
    almost_full_P1<=0;
    almost_full_P2<=0;
    almost_full_P3<=0;
	@(posedge clk);
    almost_full_P0<=0;
    almost_full_P1<=1;
    almost_full_P2<=0;
    almost_full_P3<=0;
	@(posedge clk);


    // Relleno de tiempo para analizar la senal
	@(posedge clk);
	@(posedge clk);
	@(posedge clk);
	@(posedge clk);
	@(posedge clk);
	@(posedge clk);
	@(posedge clk);
	@(posedge clk);

	$finish;
	end
	initial clk <= 1;
	always #1 clk <= ~clk;


endmodule

Arbitro/arbitro_sint.v
/* Generated by Yosys 0.9 (git sha1 1979e0b) */

(* cells_not_processed =  1  *)
(* src = "arbitro_sint.v:1" *)
module arbitro_sint(clk, reset, almost_full_P0, almost_full_P1, almost_full_P2, almost_full_P3, empty_P0, empty_P1, empty_P2, empty_P3, empty_P4, empty_P5, empty_P6, empty_P7, pop_F0_sint, pop_F1_sint, pop_F2_sint, pop_F3_sint, push_F0_sint, push_F1_sint, push_F2_sint, push_F3_sint);
  (* src = "arbitro_sint.v:37" *)
  wire _00_;
  (* src = "arbitro_sint.v:37" *)
  wire _01_;
  (* src = "arbitro_sint.v:37" *)
  wire _02_;
  (* src = "arbitro_sint.v:37" *)
  wire _03_;
  (* src = "arbitro_sint.v:37" *)
  wire _04_;
  (* src = "arbitro_sint.v:80" *)
  wire _05_;
  (* src = "arbitro_sint.v:80" *)
  wire _06_;
  (* src = "arbitro_sint.v:80" *)
  wire _07_;
  (* src = "arbitro_sint.v:44" *)
  wire _08_;
  (* src = "arbitro_sint.v:44" *)
  wire _09_;
  (* src = "arbitro_sint.v:44" *)
  wire _10_;
  (* src = "arbitro_sint.v:44" *)
  wire _11_;
  (* src = "arbitro_sint.v:44" *)
  wire _12_;
  (* src = "arbitro_sint.v:44" *)
  wire _13_;
  (* src = "arbitro_sint.v:44" *)
  wire _14_;
  wire _15_;
  wire _16_;
  wire _17_;
  wire _18_;
  wire _19_;
  wire _20_;
  wire _21_;
  wire _22_;
  wire _23_;
  wire _24_;
  wire _25_;
  wire _26_;
  wire _27_;
  wire _28_;
  wire _29_;
  wire _30_;
  wire _31_;
  wire _32_;
  wire _33_;
  wire _34_;
  wire _35_;
  (* src = "arbitro_sint.v:8" *)
  input almost_full_P0;
  (* src = "arbitro_sint.v:9" *)
  input almost_full_P1;
  (* src = "arbitro_sint.v:10" *)
  input almost_full_P2;
  (* src = "arbitro_sint.v:11" *)
  input almost_full_P3;
  (* src = "arbitro_sint.v:4" *)
  input clk;
  (* src = "arbitro_sint.v:13" *)
  input empty_P0;
  (* src = "arbitro_sint.v:14" *)
  input empty_P1;
  (* src = "arbitro_sint.v:15" *)
  input empty_P2;
  (* src = "arbitro_sint.v:16" *)
  input empty_P3;
  (* src = "arbitro_sint.v:17" *)
  input empty_P4;
  (* src = "arbitro_sint.v:18" *)
  input empty_P5;
  (* src = "arbitro_sint.v:19" *)
  input empty_P6;
  (* src = "arbitro_sint.v:20" *)
  input empty_P7;
  (* src = "arbitro_sint.v:24" *)
  output pop_F0_sint;
  reg pop_F0_sint;
  (* src = "arbitro_sint.v:25" *)
  output pop_F1_sint;
  reg pop_F1_sint;
  (* src = "arbitro_sint.v:26" *)
  output pop_F2_sint;
  reg pop_F2_sint;
  (* src = "arbitro_sint.v:27" *)
  output pop_F3_sint;
  reg pop_F3_sint;
  (* src = "arbitro_sint.v:29" *)
  output push_F0_sint;
  (* src = "arbitro_sint.v:30" *)
  output push_F1_sint;
  (* src = "arbitro_sint.v:31" *)
  output push_F2_sint;
  (* src = "arbitro_sint.v:32" *)
  output push_F3_sint;
  reg push_F3_sint;
  (* src = "arbitro_sint.v:4" *)
  input reset;
  assign _05_ = _08_ && (* src = "arbitro_sint.v:80" *) _09_;
  assign _06_ = _05_ && (* src = "arbitro_sint.v:80" *) _10_;
  assign _07_ = _06_ && (* src = "arbitro_sint.v:80" *) _11_;
  assign _08_ = ~ (* src = "arbitro_sint.v:80" *) almost_full_P0;
  assign _09_ = ~ (* src = "arbitro_sint.v:80" *) almost_full_P1;
  assign _10_ = ~ (* src = "arbitro_sint.v:80" *) almost_full_P2;
  assign _11_ = ~ (* src = "arbitro_sint.v:80" *) almost_full_P3;
  assign _12_ = _08_ | (* src = "arbitro_sint.v:44" *) _09_;
  assign _13_ = _12_ | (* src = "arbitro_sint.v:44" *) _10_;
  assign _14_ = _13_ | (* src = "arbitro_sint.v:44" *) _11_;
  always @(posedge clk)
      pop_F0_sint <= _00_;
  always @(posedge clk)
      pop_F1_sint <= _01_;
  always @(posedge clk)
      pop_F2_sint <= _02_;
  always @(posedge clk)
      pop_F3_sint <= _03_;
  always @(posedge clk)
      push_F3_sint <= _04_;
  assign _15_ = empty_P0 ? (* full_case = 32'd1 *) (* src = "arbitro_sint.v:46" *) _35_ : 1'h0;
  assign _16_ = _14_ ? (* src = "arbitro_sint.v:44" *) _15_ : pop_F1_sint;
  assign _01_ = reset ? (* full_case = 32'd1 *) (* src = "arbitro_sint.v:38" *) 1'h0 : _16_;
  assign _17_ = empty_P3 ? (* src = "arbitro_sint.v:67" *) pop_F0_sint : 1'h0;
  assign _18_ = empty_P2 ? (* full_case = 32'd1 *) (* src = "arbitro_sint.v:59" *) _17_ : 1'h0;
  assign _19_ = empty_P1 ? (* full_case = 32'd1 *) (* src = "arbitro_sint.v:53" *) _18_ : 1'h0;
  assign _20_ = empty_P0 ? (* full_case = 32'd1 *) (* src = "arbitro_sint.v:46" *) _19_ : 1'h1;
  assign _21_ = _14_ ? (* src = "arbitro_sint.v:44" *) _20_ : pop_F0_sint;
  assign _00_ = reset ? (* full_case = 32'd1 *) (* src = "arbitro_sint.v:38" *) 1'h0 : _21_;
  assign _22_ = _07_ ? (* full_case = 32'd1 *) (* src = "arbitro_sint.v:80" *) 1'h1 : 1'h0;
  assign _04_ = reset ? (* full_case = 32'd1 *) (* src = "arbitro_sint.v:38" *) 1'h0 : _22_;
  assign _23_ = empty_P3 ? (* src = "arbitro_sint.v:67" *) pop_F3_sint : 1'h1;
  assign _24_ = empty_P2 ? (* full_case = 32'd1 *) (* src = "arbitro_sint.v:59" *) _23_ : 1'h0;
  assign _25_ = empty_P1 ? (* full_case = 32'd1 *) (* src = "arbitro_sint.v:53" *) _24_ : 1'h0;
  assign _26_ = empty_P0 ? (* full_case = 32'd1 *) (* src = "arbitro_sint.v:46" *) _25_ : 1'h0;
  assign _27_ = _14_ ? (* src = "arbitro_sint.v:44" *) _26_ : pop_F3_sint;
  assign _03_ = reset ? (* full_case = 32'd1 *) (* src = "arbitro_sint.v:38" *) 1'h0 : _27_;
  assign _28_ = empty_P3 ? (* src = "arbitro_sint.v:67" *) pop_F2_sint : 1'h0;
  assign _29_ = empty_P2 ? (* full_case = 32'd1 *) (* src = "arbitro_sint.v:59" *) _28_ : 1'h1;
  assign _30_ = empty_P1 ? (* full_case = 32'd1 *) (* src = "arbitro_sint.v:53" *) _29_ : 1'h0;
  assign _31_ = empty_P0 ? (* full_case = 32'd1 *) (* src = "arbitro_sint.v:46" *) _30_ : 1'h0;
  assign _32_ = _14_ ? (* src = "arbitro_sint.v:44" *) _31_ : pop_F2_sint;
  assign _02_ = reset ? (* full_case = 32'd1 *) (* src = "arbitro_sint.v:38" *) 1'h0 : _32_;
  assign _33_ = empty_P3 ? (* src = "arbitro_sint.v:67" *) pop_F1_sint : 1'h0;
  assign _34_ = empty_P2 ? (* full_case = 32'd1 *) (* src = "arbitro_sint.v:59" *) _33_ : 1'h0;
  assign _35_ = empty_P1 ? (* full_case = 32'd1 *) (* src = "arbitro_sint.v:53" *) _34_ : 1'h1;
  assign push_F0_sint = push_F3_sint;
  assign push_F1_sint = push_F3_sint;
  assign push_F2_sint = push_F3_sint;
endmodule

RoundRobin/arbitro.v
module arbitro(
    // Controles generales del arbitro
            
    input  clk, reset, 

    // Entradas de alimentación de los fifos

    input  almost_full_P0,
    input  almost_full_P1,
    input  almost_full_P2,
    input  almost_full_P3,

    input  empty_P0,
    input  empty_P1,
    input  empty_P2,
    input  empty_P3,
    input  empty_P4,
    input  empty_P5,
    input  empty_P6,
    input  empty_P7,

    // Salidas para el control de los Fifos
            
    output reg pop_F0,
    output reg pop_F1,
    output reg pop_F2,
    output reg pop_F3,

    output reg push_F0,
    output reg push_F1,
    output reg push_F2,
    output reg push_F3);




always @(posedge clk) begin
    if (reset == 0) begin


        // Solamente hace POP si ninguna entrada almost full de esta en 1
        /*if (almost_full_P0 != 1 && almost_full_P1 != 1
            && almost_full_P2 != 1 && almost_full_P3 != 1)*/
            if(~almost_full_P0 | ~almost_full_P1 | ~almost_full_P2 | ~almost_full_P3) begin
            //Revisa las entradas para vaciarlos
            if (empty_P0 == 0) begin
                pop_F0 <= 1;
                pop_F1 <= 0;
                pop_F2 <= 0;
                pop_F3 <= 0;
             
            end 
            else if (empty_P1 == 0) begin
                pop_F0 <= 0;
                pop_F1 <= 1;
                pop_F2 <= 0;
                pop_F3 <= 0;
            end
            else if (empty_P2 == 0) begin
                pop_F0 <= 0;
                pop_F1 <= 0;
                pop_F2 <= 1;
                pop_F3 <= 0;
                

            end
            else if (empty_P3 == 0) begin
                pop_F0 <= 0;
                pop_F1 <= 0;
                pop_F2 <= 0;
                pop_F3 <= 1;
                
            end
 

        end



        if (~almost_full_P0 && ~almost_full_P1 && ~almost_full_P2 && ~almost_full_P3)begin
            push_F0 <= 1;
            push_F1 <= 1;
            push_F2 <= 1;
            push_F3 <= 1;
        end
        else begin
            push_F0 <= 0;
            push_F1 <= 0;
            push_F2 <= 0;
            push_F3 <= 0;
        end

        //Cuando recibe datos en los FIFOs de la salida, los saca
        /*if (almost_full_P0 == 1) begin
            push_F0 <= 0;
        end
        if (almost_full_P1 == 0) begin
            push_F1 <= 0;
        end
        if (almost_full_P2 == 0) begin
            push_F2 <= 0;
        end
        if (almost_full_P3 == 0) begin
            push_F3 <= 0;
        end*/

    end
    else if(reset == 1)begin
         push_F0 <= 0;
         push_F1 <= 0;
         push_F2 <= 0;
         push_F3 <= 0;

         pop_F0 <= 0;
         pop_F1 <= 0;
         pop_F2 <= 0;
         pop_F3 <= 0;
    end
end

endmodule

RoundRobin/bancoRoundRobin.v
`include "arbitro.v"
`include "probador_roundRobin.v"
`include "arbitro_sint.v"
module bancoRoundRobin();

    wire clk;
    wire reset;
    wire [1:0] select;

	wire almost_full_P0;
	wire almost_full_P1;
	wire almost_full_P2;
	wire almost_full_P3;

    wire empty_P0;
    wire empty_P1;
    wire empty_P2;
    wire empty_P3;

    wire pop_F0;
    wire pop_F1;
    wire pop_F2;
    wire pop_F3;

    wire push_F0;
    wire push_F1;
    wire push_F2;
    wire push_F3;

    wire [9:0] in_FIFO_0;
    wire [9:0] in_FIFO_1;
    wire [9:0] in_FIFO_2;
    wire [9:0] in_FIFO_3;

    wire [9:0] out_FIFO_0;
    wire [9:0] out_FIFO_1;
    wire [9:0] out_FIFO_2;
    wire [9:0] out_FIFO_3;

	wire [9:0] demuxIn;

    wire pop_F0_sint;
    wire pop_F1_sint;
    wire pop_F2_sint;
    wire pop_F3_sint;

    wire push_F0_sint;
    wire push_F1_sint;
    wire push_F2_sint;
    wire push_F3_sint;


	arbitro controlador( /*AUTOINST*/
			    // Outputs
			    .pop_F0		(pop_F0),
			    .pop_F1		(pop_F1),
			    .pop_F2		(pop_F2),
			    .pop_F3		(pop_F3),
			    .push_F0		(push_F0),
			    .push_F1		(push_F1),
			    .push_F2		(push_F2),
			    .push_F3		(push_F3),
			    // Inputs
			    .clk		(clk),
			    .reset		(reset),
			    .almost_full_P0	(almost_full_P0),
			    .almost_full_P1	(almost_full_P1),
			    .almost_full_P2	(almost_full_P2),
			    .almost_full_P3	(almost_full_P3),
			    .empty_P0		(empty_P0),
			    .empty_P1		(empty_P1),
			    .empty_P2		(empty_P2),
			    .empty_P3		(empty_P3),
			    .empty_P4		(empty_P4),
			    .empty_P5		(empty_P5),
			    .empty_P6		(empty_P6),
			    .empty_P7		(empty_P7));

        arbitro_sint controlador_sint( /*AUTOINST*/
				      // Outputs
				      .pop_F0_sint	(pop_F0_sint),
				      .pop_F1_sint	(pop_F1_sint),
				      .pop_F2_sint	(pop_F2_sint),
				      .pop_F3_sint	(pop_F3_sint),
				      .push_F0_sint	(push_F0_sint),
				      .push_F1_sint	(push_F1_sint),
				      .push_F2_sint	(push_F2_sint),
				      .push_F3_sint	(push_F3_sint),
				      // Inputs
				      .almost_full_P0	(almost_full_P0),
				      .almost_full_P1	(almost_full_P1),
				      .almost_full_P2	(almost_full_P2),
				      .almost_full_P3	(almost_full_P3),
				      .clk		(clk),
				      .empty_P0		(empty_P0),
				      .empty_P1		(empty_P1),
				      .empty_P2		(empty_P2),
				      .empty_P3		(empty_P3),
				      .empty_P4		(empty_P4),
				      .empty_P5		(empty_P5),
				      .empty_P6		(empty_P6),
				      .empty_P7		(empty_P7),
				      .reset		(reset));

    probador_roundRobin test( /*AUTOINST*/
			     // Outputs
			     .clk		(clk),
			     .reset		(reset),
			     .almost_full_P0	(almost_full_P0),
			     .almost_full_P1	(almost_full_P1),
			     .almost_full_P2	(almost_full_P2),
			     .almost_full_P3	(almost_full_P3),
			     .empty_P0		(empty_P0),
			     .empty_P1		(empty_P1),
			     .empty_P2		(empty_P2),
			     .empty_P3		(empty_P3),
			     .empty_P4		(empty_P4),
			     .empty_P5		(empty_P5),
			     .empty_P6		(empty_P6),
			     .empty_P7		(empty_P7),
			     // Inputs
			     .pop_F0		(pop_F0),
			     .pop_F1		(pop_F1),
			     .pop_F2		(pop_F2),
			     .pop_F3		(pop_F3),
			     .push_F0		(push_F0),
			     .push_F1		(push_F1),
			     .push_F2		(push_F2),
			     .push_F3		(push_F3),
			     .pop_F0_sint	(pop_F0_sint),
			     .pop_F1_sint	(pop_F1_sint),
			     .pop_F2_sint	(pop_F2_sint),
			     .pop_F3_sint	(pop_F3_sint),
			     .push_F0_sint	(push_F0_sint),
			     .push_F1_sint	(push_F1_sint),
			     .push_F2_sint	(push_F2_sint),
			     .push_F3_sint	(push_F3_sint));
    
endmodule

RoundRobin/roundRobin.vcd
$date
	Sun Jul 11 18:00:20 2021
$end
$version
	Icarus Verilog
$end
$timescale
	1s
$end
$scope module bancoRoundRobin $end
$var wire 1 ! reset $end
$var wire 1 " push_F3_sint $end
$var wire 1 # push_F3 $end
$var wire 1 $ push_F2_sint $end
$var wire 1 % push_F2 $end
$var wire 1 & push_F1_sint $end
$var wire 1 ' push_F1 $end
$var wire 1 ( push_F0_sint $end
$var wire 1 ) push_F0 $end
$var wire 1 * pop_F3_sint $end
$var wire 1 + pop_F3 $end
$var wire 1 , pop_F2_sint $end
$var wire 1 - pop_F2 $end
$var wire 1 . pop_F1_sint $end
$var wire 1 / pop_F1 $end
$var wire 1 0 pop_F0_sint $end
$var wire 1 1 pop_F0 $end
$var wire 1 2 empty_P7 $end
$var wire 1 3 empty_P6 $end
$var wire 1 4 empty_P5 $end
$var wire 1 5 empty_P4 $end
$var wire 1 6 empty_P3 $end
$var wire 1 7 empty_P2 $end
$var wire 1 8 empty_P1 $end
$var wire 1 9 empty_P0 $end
$var wire 1 : clk $end
$var wire 1 ; almost_full_P3 $end
$var wire 1 < almost_full_P2 $end
$var wire 1 = almost_full_P1 $end
$var wire 1 > almost_full_P0 $end
$scope module controlador $end
$var wire 1 ! reset $end
$var wire 1 2 empty_P7 $end
$var wire 1 3 empty_P6 $end
$var wire 1 4 empty_P5 $end
$var wire 1 5 empty_P4 $end
$var wire 1 6 empty_P3 $end
$var wire 1 7 empty_P2 $end
$var wire 1 8 empty_P1 $end
$var wire 1 9 empty_P0 $end
$var wire 1 : clk $end
$var wire 1 ; almost_full_P3 $end
$var wire 1 < almost_full_P2 $end
$var wire 1 = almost_full_P1 $end
$var wire 1 > almost_full_P0 $end
$var reg 1 1 pop_F0 $end
$var reg 1 / pop_F1 $end
$var reg 1 - pop_F2 $end
$var reg 1 + pop_F3 $end
$var reg 1 ) push_F0 $end
$var reg 1 ' push_F1 $end
$var reg 1 % push_F2 $end
$var reg 1 # push_F3 $end
$upscope $end
$scope module controlador_sint $end
$var wire 1 ? _05_ $end
$var wire 1 @ _06_ $end
$var wire 1 A _07_ $end
$var wire 1 B _08_ $end
$var wire 1 C _09_ $end
$var wire 1 D _10_ $end
$var wire 1 E _11_ $end
$var wire 1 F _12_ $end
$var wire 1 G _13_ $end
$var wire 1 H _14_ $end
$var wire 1 ( push_F0_sint $end
$var wire 1 & push_F1_sint $end
$var wire 1 $ push_F2_sint $end
$var wire 1 ! reset $end
$var wire 1 2 empty_P7 $end
$var wire 1 3 empty_P6 $end
$var wire 1 4 empty_P5 $end
$var wire 1 5 empty_P4 $end
$var wire 1 6 empty_P3 $end
$var wire 1 7 empty_P2 $end
$var wire 1 8 empty_P1 $end
$var wire 1 9 empty_P0 $end
$var wire 1 : clk $end
$var wire 1 ; almost_full_P3 $end
$var wire 1 < almost_full_P2 $end
$var wire 1 = almost_full_P1 $end
$var wire 1 > almost_full_P0 $end
$var wire 1 I _35_ $end
$var wire 1 J _34_ $end
$var wire 1 K _33_ $end
$var wire 1 L _32_ $end
$var wire 1 M _31_ $end
$var wire 1 N _30_ $end
$var wire 1 O _29_ $end
$var wire 1 P _28_ $end
$var wire 1 Q _27_ $end
$var wire 1 R _26_ $end
$var wire 1 S _25_ $end
$var wire 1 T _24_ $end
$var wire 1 U _23_ $end
$var wire 1 V _22_ $end
$var wire 1 W _21_ $end
$var wire 1 X _20_ $end
$var wire 1 Y _19_ $end
$var wire 1 Z _18_ $end
$var wire 1 [ _17_ $end
$var wire 1 \ _16_ $end
$var wire 1 ] _15_ $end
$var wire 1 ^ _04_ $end
$var wire 1 _ _03_ $end
$var wire 1 ` _02_ $end
$var wire 1 a _01_ $end
$var wire 1 b _00_ $end
$var reg 1 0 pop_F0_sint $end
$var reg 1 . pop_F1_sint $end
$var reg 1 , pop_F2_sint $end
$var reg 1 * pop_F3_sint $end
$var reg 1 " push_F3_sint $end
$upscope $end
$scope module test $end
$var wire 1 1 pop_F0 $end
$var wire 1 0 pop_F0_sint $end
$var wire 1 / pop_F1 $end
$var wire 1 . pop_F1_sint $end
$var wire 1 - pop_F2 $end
$var wire 1 , pop_F2_sint $end
$var wire 1 + pop_F3 $end
$var wire 1 * pop_F3_sint $end
$var wire 1 ) push_F0 $end
$var wire 1 ( push_F0_sint $end
$var wire 1 ' push_F1 $end
$var wire 1 & push_F1_sint $end
$var wire 1 % push_F2 $end
$var wire 1 $ push_F2_sint $end
$var wire 1 # push_F3 $end
$var wire 1 " push_F3_sint $end
$var reg 1 > almost_full_P0 $end
$var reg 1 = almost_full_P1 $end
$var reg 1 < almost_full_P2 $end
$var reg 1 ; almost_full_P3 $end
$var reg 1 : clk $end
$var reg 1 9 empty_P0 $end
$var reg 1 8 empty_P1 $end
$var reg 1 7 empty_P2 $end
$var reg 1 6 empty_P3 $end
$var reg 1 5 empty_P4 $end
$var reg 1 4 empty_P5 $end
$var reg 1 3 empty_P6 $end
$var reg 1 2 empty_P7 $end
$var reg 1 ! reset $end
$upscope $end
$upscope $end
$enddefinitions $end
#0
$dumpvars
1b
0a
0`
0_
1^
0]
0\
0[
0Z
0Y
1X
1W
1V
1U
0T
0S
0R
0Q
0P
1O
0N
0M
0L
0K
0J
1I
1H
1G
1F
1E
1D
1C
1B
1A
1@
1?
0>
0=
0<
0;
1:
09
08
07
06
x5
x4
x3
x2
01
00
0/
0.
0-
0,
0+
0*
0)
0(
0'
0&
0%
0$
0#
0"
0!
$end
#1
0:
#2
0b
1a
0W
1\
0X
1]
19
1$
1&
1(
1"
10
1#
1%
1'
1)
11
1:
#3
0:
#4
0a
1`
0\
1L
0]
1M
0I
1N
1/
01
00
1.
18
1:
#5
0:
#6
0`
1_
0L
1Q
0M
1R
0N
1S
0O
1T
17
1,
0.
1-
0/
1:
#7
0:
#8
1+
0-
0,
1*
16
1:
#9
0:
#10
0_
1b
0Q
1W
1O
0T
1I
0S
0R
1X
06
07
08
09
1:
#11
0:
#12
0+
11
10
0*
1:
#13
0:
#14
02
03
04
05
1:
#15
0:
#16
1:
#17
0:
#18
0^
0V
0A
0@
0?
0B
1>
1:
#19
0:
#20
0C
1B
0#
0%
0'
0)
0$
0&
0(
0"
1=
0>
1:
