RoundRobin/probador_roundRobin.v

module probador_roundRobin(

	output reg  clk, reset, 

    // Entradas de alimentación de los fifos

    output reg  almost_full_P0,
    output reg  almost_full_P1,
    output reg  almost_full_P2,
    output reg  almost_full_P3,

    output reg  empty_P0,
    output reg  empty_P1,
    output reg  empty_P2,
    output reg  empty_P3,
    output reg  empty_P4,
    output reg  empty_P5,
    output reg  empty_P6,
    output reg  empty_P7,

    // Salidas para el control de los Fifos
            
    input pop_F0,
    input pop_F1,
    input pop_F2,
    input pop_F3,

    input push_F0,
    input push_F1,
    input push_F2,
    input push_F3,

    // Datos de salida y entrada de los fifos

    output reg [9:0] in_FIFO_0,
    output reg [9:0] in_FIFO_1,
    output reg [9:0] in_FIFO_2,
    output reg [9:0] in_FIFO_3,

    input [9:0] out_FIFO_0,
    input [9:0] out_FIFO_1,
    input [9:0] out_FIFO_2,
    input [9:0] out_FIFO_3);


	initial begin
	$dumpfile("roundRobin.vcd");
	$dumpvars;

	clk <= 0;   
	reset <= 1;

    almost_full_P0<=0;
    almost_full_P1<=0;
    almost_full_P2<=0;
    almost_full_P3<=0;


    empty_P0 <= 0;
    empty_P1 <= 0;
    empty_P2 <= 0;
    empty_P3 <= 0;

    @(posedge clk);
	reset <= 0;

    

    empty_P0 <= 0;
    empty_P1 <= 0;
    empty_P2 <= 0;
    empty_P3 <= 0;
    @(posedge clk);
    empty_P0 <= 1;
    empty_P1 <= 0;
    empty_P2 <= 0;
    empty_P3 <= 0;    
	@(posedge clk);
    empty_P0 <= 1;
    empty_P1 <= 1;
    empty_P2 <= 0;
    empty_P3 <= 0; 

	@(posedge clk);
    empty_P0 <= 1;
    empty_P1 <= 1;
    empty_P2 <= 1;
    empty_P3 <= 0;     
	@(posedge clk);
    empty_P0 <= 1;
    empty_P1 <= 1;
    empty_P2 <= 1;
    empty_P3 <= 1;     
    @(posedge clk);

    empty_P0 <= 0;
    empty_P1 <= 0;
    empty_P2 <= 0;
    empty_P3 <= 0;
    @(posedge clk);

	@(posedge clk);
	reset  <= 0;


    empty_P0 <= 0;
    empty_P1 <= 0;
    empty_P2 <= 0;
    empty_P3 <= 0;
    empty_P4 <= 0;
    empty_P5 <= 0;
    empty_P6 <= 0;
    empty_P7 <= 0;

	@(posedge clk);
	reset  <= 0;
	@(posedge clk);
    almost_full_P0<=1;
    almost_full_P1<=0;
    almost_full_P2<=0;
    almost_full_P3<=0;
	@(posedge clk);
    almost_full_P0<=0;
    almost_full_P1<=1;
    almost_full_P2<=0;
    almost_full_P3<=0;
	@(posedge clk);


    // Relleno de tiempo para analizar la senal
	@(posedge clk);
	@(posedge clk);
	@(posedge clk);
	@(posedge clk);
	@(posedge clk);
	@(posedge clk);
	@(posedge clk);
	@(posedge clk);

	$finish;
	end
	initial clk <= 1;
	always #1 clk <= ~clk;


endmodule

RoundRobin/arbitro.v
module arbitro(
    // Controles generales del arbitro
            
    input  clk, reset, 

    // Entradas de alimentación de los fifos

    input  almost_full_P0,
    input  almost_full_P1,
    input  almost_full_P2,
    input  almost_full_P3,

    input  empty_P0,
    input  empty_P1,
    input  empty_P2,
    input  empty_P3,
    input  empty_P4,
    input  empty_P5,
    input  empty_P6,
    input  empty_P7,

    // Salidas para el control de los Fifos
            
    output reg pop_F0,
    output reg pop_F1,
    output reg pop_F2,
    output reg pop_F3,

    output reg push_F0,
    output reg push_F1,
    output reg push_F2,
    output reg push_F3,

    // Datos de salida y entrada de los fifos

    input [9:0] in_FIFO_0,
    input [9:0] in_FIFO_1,
    input [9:0] in_FIFO_2,
    input [9:0] in_FIFO_3,

    output reg [9:0] out_FIFO_0,
    output reg [9:0] out_FIFO_1,
    output reg [9:0] out_FIFO_2,
    output reg [9:0] out_FIFO_3);




always @(posedge clk) begin
    if (reset == 0) begin


        // Solamente hace POP si ninguna entrada almost full de esta en 1
        /*if (almost_full_P0 != 1 && almost_full_P1 != 1
            && almost_full_P2 != 1 && almost_full_P3 != 1)*/
            if(~almost_full_P0 | ~almost_full_P1 | ~almost_full_P2 | ~almost_full_P3) begin
            //Revisa las entradas para vaciarlos
            if (empty_P0 == 0) begin
                pop_F0 <= 1;
                pop_F1 <= 0;
                pop_F2 <= 0;
                pop_F3 <= 0;
             
            end 
            else if (empty_P1 == 0) begin
                pop_F0 <= 0;
                pop_F1 <= 1;
                pop_F2 <= 0;
                pop_F3 <= 0;
            end
            else if (empty_P2 == 0) begin
                pop_F0 <= 0;
                pop_F1 <= 0;
                pop_F2 <= 1;
                pop_F3 <= 0;
                

            end
            else if (empty_P3 == 0) begin
                pop_F0 <= 0;
                pop_F1 <= 0;
                pop_F2 <= 0;
                pop_F3 <= 1;
                
            end
 

        end



        if (~almost_full_P0 && ~almost_full_P1 && ~almost_full_P2 && ~almost_full_P3)begin
            push_F0 <= 1;
            push_F1 <= 1;
            push_F2 <= 1;
            push_F3 <= 1;
        end
        else begin
            push_F0 <= 0;
            push_F1 <= 0;
            push_F2 <= 0;
            push_F3 <= 0;
        end

        //Cuando recibe datos en los FIFOs de la salida, los saca
        /*if (almost_full_P0 == 1) begin
            push_F0 <= 0;
        end
        if (almost_full_P1 == 0) begin
            push_F1 <= 0;
        end
        if (almost_full_P2 == 0) begin
            push_F2 <= 0;
        end
        if (almost_full_P3 == 0) begin
            push_F3 <= 0;
        end*/

    end
    else if(reset == 1)begin
         push_F0 <= 0;
         push_F1 <= 0;
         push_F2 <= 0;
         push_F3 <= 0;

         pop_F0 <= 0;
         pop_F1 <= 0;
         pop_F2 <= 0;
         pop_F3 <= 0;
    end
end

endmodule

RoundRobin/bancoRoundRobin.v
`include "arbitro.v"
`include "probador_roundRobin.v"

module bancoRoundRobin();

    wire clk;
    wire reset;
    wire [1:0] select;

	wire almost_full_P0;
	wire almost_full_P1;
	wire almost_full_P2;
	wire almost_full_P3;

    wire empty_P0;
    wire empty_P1;
    wire empty_P2;
    wire empty_P3;

    wire pop_F0;
    wire pop_F1;
    wire pop_F2;
    wire pop_F3;

    wire push_F0;
    wire push_F1;
    wire push_F2;
    wire push_F3;

    wire [9:0] in_FIFO_0;
    wire [9:0] in_FIFO_1;
    wire [9:0] in_FIFO_2;
    wire [9:0] in_FIFO_3;

    wire [9:0] out_FIFO_0;
    wire [9:0] out_FIFO_1;
    wire [9:0] out_FIFO_2;
    wire [9:0] out_FIFO_3;

	wire [9:0] demuxIn;

	arbitro controlador(
		.clk    (clk),
		.reset  (reset),
        
        .almost_full_P0 (almost_full_P0),
        .almost_full_P1 (almost_full_P1),
        .almost_full_P2 (almost_full_P2),
        .almost_full_P3 (almost_full_P3),

        .empty_P0(empty_P0),
        .empty_P1(empty_P1),
        .empty_P2(empty_P2),
        .empty_P3(empty_P3),

        .pop_F0(pop_F0),
        .pop_F1(pop_F1),
        .pop_F2(pop_F2),
        .pop_F3(pop_F3),

        .push_F0(push_F0),
        .push_F1(push_F1),
        .push_F2(push_F2),
        .push_F3(push_F3),

        .in_FIFO_0(in_FIFO_0),
        .in_FIFO_1(in_FIFO_1),
        .in_FIFO_2(in_FIFO_2),
        .in_FIFO_3(in_FIFO_3),

        .out_FIFO_0(out_FIFO_0),
        .out_FIFO_1(out_FIFO_1),
        .out_FIFO_2(out_FIFO_2),
        .out_FIFO_3(out_FIFO_3));

    probador_roundRobin test(
        .clk    (clk),
		.reset  (reset),
        
        .almost_full_P0 (almost_full_P0),
        .almost_full_P1 (almost_full_P1),
        .almost_full_P2 (almost_full_P2),
        .almost_full_P3 (almost_full_P3),

        .empty_P0(empty_P0),
        .empty_P1(empty_P1),
        .empty_P2(empty_P2),
        .empty_P3(empty_P3),

        .pop_F0(pop_F0),
        .pop_F1(pop_F1),
        .pop_F2(pop_F2),
        .pop_F3(pop_F3),

        .push_F0(push_F0),
        .push_F1(push_F1),
        .push_F2(push_F2),
        .push_F3(push_F3),

        .in_FIFO_0(in_FIFO_0),
        .in_FIFO_1(in_FIFO_1),
        .in_FIFO_2(in_FIFO_2),
        .in_FIFO_3(in_FIFO_3),

        .out_FIFO_0(out_FIFO_0),
        .out_FIFO_1(out_FIFO_1),
        .out_FIFO_2(out_FIFO_2),
        .out_FIFO_3(out_FIFO_3));
    
endmodule

RoundRobin/roundRobin.vcd
$date
	Wed Jul  7 14:18:56 2021
$end
$version
	Icarus Verilog
$end
$timescale
	1s
$end
$scope module bancoRoundRobin $end
$var wire 1 ! reset $end
$var wire 1 " push_F3 $end
$var wire 1 # push_F2 $end
$var wire 1 $ push_F1 $end
$var wire 1 % push_F0 $end
$var wire 1 & pop_F3 $end
$var wire 1 ' pop_F2 $end
$var wire 1 ( pop_F1 $end
$var wire 1 ) pop_F0 $end
$var wire 10 * out_FIFO_3 [9:0] $end
$var wire 10 + out_FIFO_2 [9:0] $end
$var wire 10 , out_FIFO_1 [9:0] $end
$var wire 10 - out_FIFO_0 [9:0] $end
$var wire 10 . in_FIFO_3 [9:0] $end
$var wire 10 / in_FIFO_2 [9:0] $end
$var wire 10 0 in_FIFO_1 [9:0] $end
$var wire 10 1 in_FIFO_0 [9:0] $end
$var wire 1 2 empty_P3 $end
$var wire 1 3 empty_P2 $end
$var wire 1 4 empty_P1 $end
$var wire 1 5 empty_P0 $end
$var wire 1 6 clk $end
$var wire 1 7 almost_full_P3 $end
$var wire 1 8 almost_full_P2 $end
$var wire 1 9 almost_full_P1 $end
$var wire 1 : almost_full_P0 $end
$scope module controlador $end
$var wire 1 ; empty_P4 $end
$var wire 1 < empty_P5 $end
$var wire 1 = empty_P6 $end
$var wire 1 > empty_P7 $end
$var wire 1 ! reset $end
$var wire 10 ? in_FIFO_3 [9:0] $end
$var wire 10 @ in_FIFO_2 [9:0] $end
$var wire 10 A in_FIFO_1 [9:0] $end
$var wire 10 B in_FIFO_0 [9:0] $end
$var wire 1 2 empty_P3 $end
$var wire 1 3 empty_P2 $end
$var wire 1 4 empty_P1 $end
$var wire 1 5 empty_P0 $end
$var wire 1 6 clk $end
$var wire 1 7 almost_full_P3 $end
$var wire 1 8 almost_full_P2 $end
$var wire 1 9 almost_full_P1 $end
$var wire 1 : almost_full_P0 $end
$var reg 10 C out_FIFO_0 [9:0] $end
$var reg 10 D out_FIFO_1 [9:0] $end
$var reg 10 E out_FIFO_2 [9:0] $end
$var reg 10 F out_FIFO_3 [9:0] $end
$var reg 1 ) pop_F0 $end
$var reg 1 ( pop_F1 $end
$var reg 1 ' pop_F2 $end
$var reg 1 & pop_F3 $end
$var reg 1 % push_F0 $end
$var reg 1 $ push_F1 $end
$var reg 1 # push_F2 $end
$var reg 1 " push_F3 $end
$upscope $end
$scope module test $end
$var wire 10 G out_FIFO_0 [9:0] $end
$var wire 10 H out_FIFO_1 [9:0] $end
$var wire 10 I out_FIFO_2 [9:0] $end
$var wire 10 J out_FIFO_3 [9:0] $end
$var wire 1 ) pop_F0 $end
$var wire 1 ( pop_F1 $end
$var wire 1 ' pop_F2 $end
$var wire 1 & pop_F3 $end
$var wire 1 % push_F0 $end
$var wire 1 $ push_F1 $end
$var wire 1 # push_F2 $end
$var wire 1 " push_F3 $end
$var reg 1 : almost_full_P0 $end
$var reg 1 9 almost_full_P1 $end
$var reg 1 8 almost_full_P2 $end
$var reg 1 7 almost_full_P3 $end
$var reg 1 6 clk $end
$var reg 1 5 empty_P0 $end
$var reg 1 4 empty_P1 $end
$var reg 1 3 empty_P2 $end
$var reg 1 2 empty_P3 $end
$var reg 1 K empty_P4 $end
$var reg 1 L empty_P5 $end
$var reg 1 M empty_P6 $end
$var reg 1 N empty_P7 $end
$var reg 10 O in_FIFO_0 [9:0] $end
$var reg 10 P in_FIFO_1 [9:0] $end
$var reg 10 Q in_FIFO_2 [9:0] $end
$var reg 10 R in_FIFO_3 [9:0] $end
$var reg 1 ! reset $end
$upscope $end
$upscope $end
$enddefinitions $end
#0
$dumpvars
bx R
bx Q
bx P
bx O
xN
xM
xL
xK
bx J
bx I
bx H
bx G
bx F
bx E
bx D
bx C
bx B
bx A
bx @
bx ?
z>
z=
z<
z;
0:
09
08
07
16
05
04
03
02
bx 1
bx 0
bx /
bx .
bx -
bx ,
bx +
bx *
0)
0(
0'
0&
0%
0$
0#
0"
0!
$end
#1
06
#2
15
1"
1#
1$
1%
1)
16
#3
06
#4
1(
0)
14
16
#5
06
#6
13
1'
0(
16
#7
06
#8
1&
0'
12
16
#9
06
#10
02
03
04
05
16
#11
06
#12
0&
1)
16
#13
06
#14
0N
0M
0L
0K
16
#15
06
#16
16
#17
06
#18
1:
16
#19
06
#20
0"
0#
0$
0%
19
0:
16
